[{"Id":1,"Name":"APDP","Description":"Applied Programming and Design Principles","Status":"Active"},{"Id":2,"Name":"BPS","Description":"Business Process Support","Status":"Deactive"},{"Id":3,"Name":"DM","Description":"Discrete Maths","Status":"Deactive"},{"Id":4,"Name":"DSAA","Description":"Data Structures and Algorithms","Status":"Active"},{"Id":5,"Name":"Hello","Description":"Hi","Status":"Active"},{"Id":6,"Name":"Good Luck","Description":"re","Status":"Deactive"},{"Id":7,"Name":"d","Description":"www","Status":"Active"}]